CHANGES.txt
CONTRIBUTORS.txt
MANIFEST.in
README.txt
setup.py
collective/__init__.py
collective.recipe.patch.egg-info/PKG-INFO
collective.recipe.patch.egg-info/SOURCES.txt
collective.recipe.patch.egg-info/dependency_links.txt
collective.recipe.patch.egg-info/entry_points.txt
collective.recipe.patch.egg-info/namespace_packages.txt
collective.recipe.patch.egg-info/requires.txt
collective.recipe.patch.egg-info/top_level.txt
collective.recipe.patch.egg-info/zip-safe
collective/recipe/__init__.py
collective/recipe/patch/README.txt
collective/recipe/patch/__init__.py
collective/recipe/patch/patch.py
collective/recipe/patch/tests/__init__.py
collective/recipe/patch/tests/test_docs.py