Metadata-Version: 1.0
Name: collective.recipe.patch
Version: 0.2.2
Summary: recipe for patching eggs
Home-page: http://github.com/garbas/collective.recipe.patch
Author: Rok Garbas
Author-email: rok.garbas@gmail.com
License: GPL
Keywords: buildout recipe patch
Platform: UNKNOWN
Classifier: Framework :: Buildout
Classifier: Intended Audience :: Developers
Classifier: Topic :: Software Development :: Build Tools
Classifier: Topic :: Software Development :: Libraries :: Python Modules
Classifier: License :: OSI Approved :: GNU General Public License (GPL)
